README.rst
gepard.py
setup.cfg
setup.py
gepard_python.egg-info/PKG-INFO
gepard_python.egg-info/SOURCES.txt
gepard_python.egg-info/dependency_links.txt
gepard_python.egg-info/requires.txt
gepard_python.egg-info/top_level.txt