Metadata-Version: 1.0
Name: gepard-python
Version: 1.0.9
Summary: Python client for gepard:General purpose communications for distributed applications / Microservices / events, semaphores and messages for JavaScript, Java, Python and PHP
Home-page: https://github.com/gessinger-hj/gepard-python
Author: Hans-Juergen Gessinger
Author-email: gessinger.hj@gmail.com
License: UNKNOWN
Keywords: distributed-applications events semaphores locks messages JavaScript Java Python PHP messages
Platform: UNKNOWN
